README.md
setup.py
aiomixpanel/__init__.py
aiomixpanel/aioconsumer.py
aiomixpanel.egg-info/PKG-INFO
aiomixpanel.egg-info/SOURCES.txt
aiomixpanel.egg-info/dependency_links.txt
aiomixpanel.egg-info/requires.txt
aiomixpanel.egg-info/top_level.txt