Metadata-Version: 1.0
Name: aiomixpanel
Version: 1.1.0
Summary: aiohttp-based mixpanel consumer for python3
Home-page: https://github.com/jonathan-shemer/aiomixpanel
Author: Jonathan Shemer
Author-email: UNKNOWN
License: GNUv3
Platform: UNKNOWN
